example_pkg/__init__.py
gotrans/__init__.py
gotrans/translate.py
gotrans-0.0.1.dist-info/METADATA
gotrans-0.0.1.dist-info/RECORD
gotrans-0.0.1.dist-info/WHEEL
gotrans-0.0.1.dist-info/top_level.txt
quotool/__init__.py
quotool/quo_down.py
