Metadata-Version: 2.1
Name: gotrans
Version: 0.0.1
Summary: google trans
Home-page: https://github.com/Olaful/
Author: taner
Author-email: taner@example.com
License: UNKNOWN
Platform: UNKNOWN
Classifier: Programming Language :: Python :: 3
Classifier: License :: OSI Approved :: MIT License
Classifier: Operating System :: OS Independent
Requires-Python: >=3.6
